{
  "updated_at": "2026-06-24 10:05:07 CST",
  "updated_at_utc": "2026-06-24 02:05:07 UTC",
  "state": "OBSERVE",
  "state_days": 8,
  "headline": "No trigger B=1 C=0 E=2",
  "recommendation": "OBSERVE",
  "attribution": "鹰派重定价 (前端引领)",
  "vix": 19.49,
  "vix3m": 21.06,
  "vix_vix3m_ratio": 0.925,
  "hyg_lqd_z": {
    "hyg_z": 1.42,
    "lqd_z": 0.764,
    "spread_z": 0.656
  },
  "hyg_lqd": 0.7334,
  "ten_year": 4.493,
  "scores": {
    "hawkish": 3,
    "dovish": 1,
    "liquidity": 0,
    "inflation": 1,
    "growth": 2
  },
  "gates": {
    "vix_contango": true,
    "casc": true,
    "credit": true
  },
  "upgrade_needs": [
    "B>=3 (now 1/4)",
    "E<=1 (now 2/3)"
  ]
}